TheforgerSWin32ApiJiaochengDierBanJiantizhongwen/README.md
TheforgerSWin32ApiJiaochengDierBanJiantizhongwen/__init__.py
TheforgerSWin32ApiJiaochengDierBanJiantizhongwen/__main__.py
TheforgerSWin32ApiJiaochengDierBanJiantizhongwen/file.epub
TheforgerSWin32ApiJiaochengDierBanJiantizhongwen/index.html
TheforgerSWin32ApiJiaochengDierBanJiantizhongwen/css/__init__.py
TheforgerSWin32ApiJiaochengDierBanJiantizhongwen/css/annotations.css
TheforgerSWin32ApiJiaochengDierBanJiantizhongwen/css/main.css
TheforgerSWin32ApiJiaochengDierBanJiantizhongwen/css/normalize.css
TheforgerSWin32ApiJiaochengDierBanJiantizhongwen/css/popup.css
TheforgerSWin32ApiJiaochengDierBanJiantizhongwen/font/__init__.py
TheforgerSWin32ApiJiaochengDierBanJiantizhongwen/font/fontello.eot
TheforgerSWin32ApiJiaochengDierBanJiantizhongwen/font/fontello.svg
TheforgerSWin32ApiJiaochengDierBanJiantizhongwen/font/fontello.ttf
TheforgerSWin32ApiJiaochengDierBanJiantizhongwen/font/fontello.woff
TheforgerSWin32ApiJiaochengDierBanJiantizhongwen/img/__init__.py
TheforgerSWin32ApiJiaochengDierBanJiantizhongwen/img/annotator-glyph-sprite.png
TheforgerSWin32ApiJiaochengDierBanJiantizhongwen/img/annotator-icon-sprite.png
TheforgerSWin32ApiJiaochengDierBanJiantizhongwen/img/apple-touch-icon.png
TheforgerSWin32ApiJiaochengDierBanJiantizhongwen/img/cancelfullscreen.png
TheforgerSWin32ApiJiaochengDierBanJiantizhongwen/img/close.png
TheforgerSWin32ApiJiaochengDierBanJiantizhongwen/img/fullscreen.png
TheforgerSWin32ApiJiaochengDierBanJiantizhongwen/img/loader.gif
TheforgerSWin32ApiJiaochengDierBanJiantizhongwen/img/menu-icon.png
TheforgerSWin32ApiJiaochengDierBanJiantizhongwen/img/save.png
TheforgerSWin32ApiJiaochengDierBanJiantizhongwen/img/saved.png
TheforgerSWin32ApiJiaochengDierBanJiantizhongwen/img/settings-s.png
TheforgerSWin32ApiJiaochengDierBanJiantizhongwen/img/settings.png
TheforgerSWin32ApiJiaochengDierBanJiantizhongwen/img/star.png
TheforgerSWin32ApiJiaochengDierBanJiantizhongwen/js/__init__.py
theforger_s_win32_api_jiaocheng_dier_ban_jiantizhongwen-2024.3.2.0.dist-info/METADATA
theforger_s_win32_api_jiaocheng_dier_ban_jiantizhongwen-2024.3.2.0.dist-info/WHEEL
theforger_s_win32_api_jiaocheng_dier_ban_jiantizhongwen-2024.3.2.0.dist-info/entry_points.txt
theforger_s_win32_api_jiaocheng_dier_ban_jiantizhongwen-2024.3.2.0.dist-info/top_level.txt
theforger_s_win32_api_jiaocheng_dier_ban_jiantizhongwen-2024.3.2.0.dist-info/RECORD
